outlier_detector/__init__.py
outlier_detector/decorators.py
outlier_detector/detectors.py
outlier_detector/filters.py
outlier_detector/functions.py
test/__init__.py
test/end_to_end.py
test/integration.py
test/readme.py
test/unit.py
outlier_detector-0.0.2.dist-info/LICENSE
outlier_detector-0.0.2.dist-info/METADATA
outlier_detector-0.0.2.dist-info/WHEEL
outlier_detector-0.0.2.dist-info/top_level.txt
outlier_detector-0.0.2.dist-info/RECORD
