Metadata-Version: 2.1
Name: outlier-detector
Version: 0.0.2
Summary: Minimal tool for outliers detection on small samples set
Home-page: https://github.com/docet85/outlier_detector
Author: Fabio Veronese
Author-email: fveronese85@gmail.com
License: UNKNOWN
Platform: UNKNOWN
Classifier: Programming Language :: Python :: 3
Classifier: License :: OSI Approved :: MIT License
Classifier: Operating System :: OS Independent
Requires-Python: >=3.6
